isilon_sdk/__init__.py
isilon_sdk/v9_4_0/__init__.py
isilon_sdk/v9_4_0/api_client.py
isilon_sdk/v9_4_0/configuration.py
isilon_sdk/v9_4_0/rest.py
isilon_sdk/v9_4_0/api/__init__.py
isilon_sdk/v9_4_0/api/antivirus_api.py
isilon_sdk/v9_4_0/api/api_api.py
isilon_sdk/v9_4_0/api/audit_api.py
isilon_sdk/v9_4_0/api/auth_api.py
isilon_sdk/v9_4_0/api/auth_groups_api.py
isilon_sdk/v9_4_0/api/auth_providers_api.py
isilon_sdk/v9_4_0/api/auth_roles_api.py
isilon_sdk/v9_4_0/api/auth_users_api.py
isilon_sdk/v9_4_0/api/avscan_api.py
isilon_sdk/v9_4_0/api/avscan_nodes_api.py
isilon_sdk/v9_4_0/api/catalog_api.py
isilon_sdk/v9_4_0/api/certificate_api.py
isilon_sdk/v9_4_0/api/cloud_api.py
isilon_sdk/v9_4_0/api/cluster_api.py
isilon_sdk/v9_4_0/api/cluster_mode_api.py
isilon_sdk/v9_4_0/api/cluster_nodes_api.py
isilon_sdk/v9_4_0/api/config_api.py
isilon_sdk/v9_4_0/api/datamover_api.py
isilon_sdk/v9_4_0/api/debug_api.py
isilon_sdk/v9_4_0/api/dedupe_api.py
isilon_sdk/v9_4_0/api/event_api.py
isilon_sdk/v9_4_0/api/file_filter_api.py
isilon_sdk/v9_4_0/api/filepool_api.py
isilon_sdk/v9_4_0/api/filesystem_api.py
isilon_sdk/v9_4_0/api/fsa_api.py
isilon_sdk/v9_4_0/api/fsa_index_api.py
isilon_sdk/v9_4_0/api/fsa_results_api.py
isilon_sdk/v9_4_0/api/groupnets_summary_api.py
isilon_sdk/v9_4_0/api/hardening_api.py
isilon_sdk/v9_4_0/api/hardware_api.py
isilon_sdk/v9_4_0/api/healthcheck_api.py
isilon_sdk/v9_4_0/api/id_resolution_api.py
isilon_sdk/v9_4_0/api/id_resolution_zones_api.py
isilon_sdk/v9_4_0/api/ipmi_api.py
isilon_sdk/v9_4_0/api/job_api.py
isilon_sdk/v9_4_0/api/keymanager_api.py
isilon_sdk/v9_4_0/api/lfn_api.py
isilon_sdk/v9_4_0/api/license_api.py
isilon_sdk/v9_4_0/api/local_api.py
isilon_sdk/v9_4_0/api/local_cluster_api.py
isilon_sdk/v9_4_0/api/namespace_api.py
isilon_sdk/v9_4_0/api/network_api.py
isilon_sdk/v9_4_0/api/network_groupnets_api.py
isilon_sdk/v9_4_0/api/network_groupnets_subnets_api.py
isilon_sdk/v9_4_0/api/papi_api.py
isilon_sdk/v9_4_0/api/performance_api.py
isilon_sdk_thaonv-0.1.0.dist-info/METADATA
isilon_sdk_thaonv-0.1.0.dist-info/WHEEL
isilon_sdk_thaonv-0.1.0.dist-info/top_level.txt
isilon_sdk_thaonv-0.1.0.dist-info/RECORD
